d3a_interface/__init__.py
gsy_framework/__init__.py
gsy_framework/area_validator.py
gsy_framework/constants_limits.py
gsy_framework/data_classes.py
gsy_framework/enums.py
gsy_framework/exceptions.py
gsy_framework/read_user_profile.py
gsy_framework/results_validator.py
gsy_framework/scenario_validators.py
gsy_framework/schemas.py
gsy_framework/settings_validators.py
gsy_framework/unit_test_utils.py
gsy_framework/utils.py
gsy_framework/api_simulation_config/__init__.py
gsy_framework/api_simulation_config/validators.py
gsy_framework/client_connections/__init__.py
gsy_framework/client_connections/constants.py
gsy_framework/client_connections/utils.py
gsy_framework/client_connections/websocket_connection.py
gsy_framework/kafka_communication/__init__.py
gsy_framework/kafka_communication/kafka_consumer.py
gsy_framework/kafka_communication/kafka_producer.py
gsy_framework/matching_algorithms/__init__.py
gsy_framework/matching_algorithms/abstract_matching_algorithm.py
gsy_framework/matching_algorithms/pay_as_bid_matching_algorithm.py
gsy_framework/matching_algorithms/pay_as_clear_matching_algorithm.py
gsy_framework/matching_algorithms/requirements_validators.py
gsy_framework/sim_results/__init__.py
gsy_framework/sim_results/aggregate_results.py
gsy_framework/sim_results/all_results.py
gsy_framework/sim_results/area_throughput_stats.py
gsy_framework/sim_results/bills.py
gsy_framework/sim_results/cumulative_grid_trades.py
gsy_framework/sim_results/cumulative_net_energy_flow.py
gsy_framework/sim_results/device_statistics.py
gsy_framework/sim_results/energy_trade_profile.py
gsy_framework/sim_results/kpi.py
gsy_framework/sim_results/market_price_energy_day.py
gsy_framework/sim_results/market_summary_info.py
gsy_framework/sim_results/results_abc.py
gsy_framework/sim_results/simulation_assets_info.py
gsy_framework/validators/__init__.py
gsy_framework/validators/base_validator.py
gsy_framework/validators/cep_validator.py
gsy_framework/validators/finite_diesel_generator_validator.py
gsy_frameworke-5.0.2.dist-info/LICENSE
gsy_frameworke-5.0.2.dist-info/METADATA
gsy_frameworke-5.0.2.dist-info/WHEEL
gsy_frameworke-5.0.2.dist-info/top_level.txt
gsy_frameworke-5.0.2.dist-info/RECORD
