Metadata-Version: 2.1
Name: gsy-frameworke
Version: 5.0.2
Summary: GSy Framework
Home-page: https://github.com/gridsingularity/gsy-framework
Author: GridSingularity
Author-email: d3a@gridsingularity.com
License: UNKNOWN
Platform: UNKNOWN
License-File: LICENSE
Requires-Dist: attrs (==21.2.0)
Requires-Dist: backports.entry-points-selectable (==1.1.0)
Requires-Dist: certifi (==2021.10.8)
Requires-Dist: cfgv (==3.3.1)
Requires-Dist: chardet (==4.0.0)
Requires-Dist: distlib (==0.3.3)
Requires-Dist: entrypoints (==0.3)
Requires-Dist: filelock (==3.3.2)
Requires-Dist: flake8 (==3.7.9)
Requires-Dist: flake8-tuple (==0.4.1)
Requires-Dist: identify (==2.3.3)
Requires-Dist: idna (==2.10)
Requires-Dist: jsonschema (==4.1.2)
Requires-Dist: kafka-python (==2.0.2)
Requires-Dist: mccabe (==0.6.1)
Requires-Dist: nodeenv (==1.6.0)
Requires-Dist: packaging (==21.2)
Requires-Dist: pendulum (==2.1.2)
Requires-Dist: platformdirs (==2.4.0)
Requires-Dist: pluggy (==1.0.0)
Requires-Dist: pre-commit (==2.15.0)
Requires-Dist: py (==1.10.0)
Requires-Dist: pycodestyle (==2.5.0)
Requires-Dist: pyflakes (==2.1.1)
Requires-Dist: pyparsing (==2.4.7)
Requires-Dist: pyrsistent (==0.18.0)
Requires-Dist: python-dateutil (==2.8.2)
Requires-Dist: pytzdata (==2020.1)
Requires-Dist: pyyaml (==6.0)
Requires-Dist: redis (==3.5.3)
Requires-Dist: requests (==2.25.1)
Requires-Dist: six (==1.16.0)
Requires-Dist: tabulate (==0.8.9)
Requires-Dist: toml (==0.10.2)
Requires-Dist: tox (==3.24.4)
Requires-Dist: urllib3 (==1.26.7)
Requires-Dist: virtualenv (==20.10.0)
Requires-Dist: websockets (==10.0)
